{"published time": "2024-03-09T08-02-99", "images": ["https://armyinform.com.ua/wp-content/uploads/2024/03/russian-losses-03-09-2024-scaled.jpg"], "content": "<div class=\"single-content\"><figure class=\"post-thumbnail\"><img alt=\"\" class=\"attachment-post-thumbnail size-post-thumbnail wp-post-image\" height=\"2048\" sizes=\"(max-width: 2039px) 100vw, 2039px\" src=\"../Images/2024-03-09T08-02-99/000000.jpg\" srcset=\"../Images/2024-03-09T08-02-99/000000.jpg\" width=\"2039\"/></figure><!-- .post-thumbnail --><p><strong>The total fighting loss of the enemy from 24.02.22 to 09.03.24 are approximately:</strong></p><ul><li>personnel - 420270 (+850) persons liquidated</li><li>tanks - 6712 (+6)</li><li>combat armored vehicles - 12823 (+25)</li><li>artillery systems - 10428 (+53)</li><li>RSWW - 1012 (+1)</li><li>air defense means - 707 (+3)</li><li>aircraft - 347 (0)</li><li>helicopters - 325 (0)</li><li>UAV Operative-tactical level-8041 (+43)</li><li>Winged rockets - 1919 (0)</li><li>ships / boats - 26 (0)</li><li>submarines - 1 (0)</li><li>automobile equipment and tanks - 13683 (+85)</li><li>Special Technique - 1666 (+10)</li></ul><p>The data is specified ...</p><p>Beat the occupier! Let's win together! Our strength is in truth!</p><p>Source:<a href=\"https://www.facebook.com/GeneralStaff.ua/posts/pfbid0XyVrZngmTkZqe6u6MNzaixwtDkjBs6W1MJYQjscaiYcSkJAbtEUg4fJ6dLKt9UHGl\" rel=\"nofollow\" target=\"_blank\">The General Staff of the Armed Forces of Ukraine as of 09.03.24</a>.</p></div>", "source": "https://armyinform.com.ua/2024/03/09/vtraty-rf-za-dobu-minus-850-okupantiv-85-odynycz-avtotehniky-i-6-tankiv/", "title": "RF loss per day: minus 850 invaders, 85 units of auto engineering and 6 tanks", "description": "personnel - 420270 (+850) persons eliminated tanks - 6712 (+6) combat ...", "author": ["Army Inform"], "categories": ["\u0412\u0430\u0436\u043b\u0438\u0432\u043e", "\u041d\u043e\u0432\u0438\u043d\u0438"], "tags": ["stoprussia", "\u0430\u0433\u0440\u0435\u0441\u0456\u044f \u0440\u0444", "\u0432\u0456\u0439\u043d\u0430", "\u0432\u0442\u043e\u0440\u0433\u043d\u0435\u043d\u043d\u044f \u0440\u0444", "\u0432\u0442\u0440\u0430\u0442\u0438 \u0432\u043e\u0440\u043e\u0433\u0430", "\u0413\u0428 \u0417\u0421\u0423"]}