{"published time": "2024-03-14T17:32:00+08:00", "news source": "https://t.me/bazabazon/25857", "lng": "36.59726", "lat": "50.5785", "location": ["Belgorod", "Belgorodskaya oblast'"], "id": 22635547, "action": "dead-1", "title": "2\u4eba\u56e0\u8d1d\u5c14\u6208\u7f57\u5fb7\uff08Belgorod\uff09\u70ae\u51fb\u800c\u4e27\u751f", "images": [], "content": "<h2>2\u4eba\u56e0\u8d1d\u5c14\u6208\u7f57\u5fb7\uff08Belgorod\uff09\u70ae\u51fb\u800c\u4e27\u751f</h2><div class=\"popup_video\"></div><div class=\"popup_imgi\"></div>", "source": "https://liveuamap.com/en/2024/14-march-2-person-killed-as-result-of-shelling-in-belgorod", "author": ["Live UA Map"], "categories": ["Russia"], "tags": ["Belgorod", "Belgorodskaya oblast'"], "source_name": "LiveUAMap"}