{"published time": "2024-03-18T00:31:00+08:00", "news source": "https://t.me/dneproperatyv/91528", "lng": "34.39476", "lat": "47.56358", "location": ["Zaporizhia"], "id": 22636309, "action": "bomb-1", "title": "\u4eca\u5929\u56e0\u4eca\u5929\u5728\u5c3c\u79d1\u6ce2\u5c14\u533a\u7684\u4fc4\u7f57\u65af\u88ad\u51fb\u800c\u53d7\u4f244\u53d7\u4f24", "images": ["https://liveuamap.com/pics/2024/03/17/22636309_0.jpg", "https://liveuamap.com/pics/2024/03/17/22636309_1.jpg", "https://liveuamap.com/pics/2024/03/17/22636309_2.jpg", "https://liveuamap.com/pics/2024/03/17/22636309_3.jpg"], "content": "<h2>\u4eca\u5929\u56e0\u4eca\u5929\u5728\u5c3c\u79d1\u6ce2\u5c14\u533a\u7684\u4fc4\u7f57\u65af\u88ad\u51fb\u800c\u53d7\u4f244\u53d7\u4f24</h2><div class=\"popup_video\"></div><label><img alt=\"4 wounded today as result of Russian attacks in Nikopol district today\" src=\"../Images/2024-03-18T00-31-00-08-00/000000.jpg\" srcset=\"../Images/2024-03-18T00-31-00-08-00/000000.jpg\"/></label><div class=\"popup_imgi\"><img alt=\"4 wounded today as result of Russian attacks in Nikopol district today\" src=\"../Images/2024-03-18T00-31-00-08-00/000001.jpg\" srcset=\"../Images/2024-03-18T00-31-00-08-00/000001.jpg\"/><img alt=\"4 wounded today as result of Russian attacks in Nikopol district today\" src=\"../Images/2024-03-18T00-31-00-08-00/000002.jpg\" srcset=\"../Images/2024-03-18T00-31-00-08-00/000002.jpg\"/><img alt=\"4 wounded today as result of Russian attacks in Nikopol district today\" src=\"../Images/2024-03-18T00-31-00-08-00/000003.jpg\" srcset=\"../Images/2024-03-18T00-31-00-08-00/000003.jpg\"/></div>", "source": "https://liveuamap.com/en/2024/17-march-4-wounded-today-as-result-of-russian-attacks-in", "author": ["Live UA Map"], "categories": [], "tags": ["Zaporizhia"], "source_name": "LiveUAMap"}