{"published time": "2024-03-29T19:39:00+08:00", "images": ["https://armyinform.com.ua/wp-content/uploads/2024/03/zelenskyj_zvernennya-3.png"], "content": "<div class=\"single-content\"><figure class=\"post-thumbnail\"><img alt=\"\" class=\"attachment-post-thumbnail size-post-thumbnail wp-post-image\" height=\"1080\" sizes=\"(max-width: 1920px) 100vw, 1920px\" src=\"../Images/2024-03-29T19-39-00-08-00/000000.png\" srcset=\"../Images/2024-03-29T19-39-00-08-00/000000.png\" width=\"1920\"/></figure><!-- .post-thumbnail --><p><strong>To collect information, analyze it and propose decisions will be the SBU, the State Secretariat, Ministry of Defense and Secretary of the National Security and Defense Council.</strong></p><p>About the online casino Volodymyr Zelenskyy<a href=\"https://t.me/V_Zelenskiy_official/9924\" rel=\"nofollow\" target=\"_blank\">spoke in his evening address March 29</a>.</p><p>\u201cToday, very quickly gathered the necessary votes of the petition on the subject of casino-online platforms of gambling. About how it is widespread and how it affects part of society, \u201dthe President said.</p><p>He noted that next week he was waiting for the proposal to resolve this issue.</p><p>The petition on the President's website on the restriction of online casino in the south gained the required number of signatures.</p><p>As<a href=\"https://armyinform.com.ua/2024/03/04/vytratyv-zibrani-donaty-dlya-zsu-na-onlajn-kazyno-pered-sudom-postane-volonter-shahraj/\">reported the armyinform</a>, Kharkiv, who collected \"donate\" for the military of the Armed Forces and then spent them on online casinos, will be tried for fraud.</p><p></p></div>", "source": "https://armyinform.com.ua/2024/03/29/prezydent-nakazav-proanalizuvaty-diyalnist-onlajn-kazino/", "title": "President ordered an online casino activity to analyze", "description": "Volodymyr Zelenskyy spoke about online casino in his evening address on March 29. ...", "author": ["Army Inform"], "categories": ["\u041d\u043e\u0432\u0438\u043d\u0438"], "tags": ["\u043e\u043d\u043b\u0430\u0439\u043d-\u043a\u0430\u0437\u0438\u043d\u043e", "\u041f\u0440\u0435\u0437\u0438\u0434\u0435\u043d\u0442 \u0423\u043a\u0440\u0430\u0457\u043d\u0438"], "source_name": "ArmyInform"}