{"published time": "2024-03-30T02:18:00+08:00", "news source": "https://t.me/kharkivlife/80034", "lng": "36.42243", "lat": "50.19468", "location": ["Lyptsi"], "id": 22639107, "action": "bomb-1", "title": "Russian aviation launching guided aerial bombs towards Liptsy of Kharkiv region", "images": [], "content": "<h2>Russian aviation launching guided aerial bombs towards Liptsy of Kharkiv region</h2><div class=\"popup_video\"></div><div class=\"popup_imgi\"></div>", "source": "https://liveuamap.com/en/2024/29-march-russian-aviation-launching-guided-aerial-bombs-towards", "author": ["Live UA Map"], "categories": [], "tags": ["Lyptsi"], "source_name": "LiveUAMap"}