{"published time": "2024-03-07T22-49-00", "news source": "https://t.me/rusnews/50033", "lng": "37.87716", "lat": "59.13772", "location": ["Cherepovets,Vologodskaya oblast'"], "id": 22634068, "action": "drone-2", "title": "Drone targeted metallurgical plant in Cherepovets", "images": [], "content": "<h2>Drone targeted metallurgical plant in Cherepovets</h2><div class=\"popup_video\"><label><iframe allowfullscreen=\"\" frameborder=\"0\" height=\"337\" mozallowfullscreen=\"\" src=\"https://player.vimeo.com/video/https://t.me/rusnews/50033?embed=1embed/simple\" webkitallowfullscreen=\"\" width=\"600\"></iframe></label></div><div class=\"popup_imgi\"></div>", "source": "https://liveuamap.com/en/2024/7-march-drone-targeted-metallurgical-plant-in-cherepovets", "author": ["Live UA Map"], "categories": ["Russia"], "tags": ["Cherepovets,Vologodskaya oblast'"]}