{"published time": "2024-03-05T17-43-99", "images": ["https://armyinform.com.ua/wp-content/uploads/2024/03/stream_packshot_03.05.jpg"], "content": "<div class=\"single-content\"><figure class=\"post-thumbnail\"><img alt=\"\" class=\"attachment-post-thumbnail size-post-thumbnail wp-post-image\" height=\"720\" sizes=\"(max-width: 1280px) 100vw, 1280px\" src=\"../Images/2024-03-05T17-43-99/000000.jpg\" srcset=\"../Images/2024-03-05T17-43-99/000000.jpg\" width=\"1280\"/></figure><!-- .post-thumbnail --><p><strong>Magura V5 Sea Frones\u88ab\u4fc4\u7f57\u65af\u519b\u8230\u201c Sergey Kotov\u201d\u6467\u6bc1\u3002 \u8239\u88ab\u5de6\u53f3\u4e24\u4fa7\u635f\u574f\u3002 \u6839\u636eGur Mou\u7684\u8bf4\u6cd5\uff0c\u4e03\u540d\u4fc4\u7f57\u65af\u4eba\u88ab\u6740\uff0c\u516d\u4eba\u53d7\u4f24\u3002 \u5176\u4ed652\u540d\u673a\u7ec4\u4eba\u5458\u53ef\u80fd\u88ab\u64a4\u79bb\u3002</strong></p><p>\u5728\u963f\u592b\u8fea\u592b\u5361\uff08Avdiivka\uff09\u7684\u90ca\u533a\uff0c\u7b2c\u4e09\u4e2a\u72ec\u7acb\u7684\u7a81\u51fb\u65c5\u7684\u6218\u58eb\u88ab\u4fc4\u7f57\u65af\u4eba\u4fd8\u864f\uff0c\u4fc4\u7f57\u65af\u4eba\u201c\u88ab\u8feb\u201d\u53c2\u52a0\u6218\u4e89\u3002</p><p>\u5728\u8d6b\u5c14\u68ee\u5730\u533a\u7684\u88ab\u5360\u9886\u7684\u5730\u533a\uff0c\u7a7a\u4e2d\u529b\u91cf\u7ed9AASM-250\u9524\u7ba1\u7406\u7684AASM-2550\u6c14\u6876\u7559\u4e0b\u4e86\u6df1\u523b\u7684\u5370\u8c61\u3002</p><p>SBU\u62d8\u7559\u4e86\u8bd5\u56fe\u7834\u574fZaporozhye\u90ae\u5c40\u7684\u4fc4\u7f57\u65af\u7279\u5de5\u3002</p><p><iframe allow=\"accelerometer; autoplay; clipboard-write; encrypted-media; gyroscope; picture-in-picture; web-share\" allowfullscreen=\"\" frameborder=\"0\" height=\"480\" loading=\"lazy\" src=\"https://www.youtube.com/embed/F1QSuvjl0SI?feature=oembed\" title=\"\u041f\u041e\u0422\u041e\u041f\u0418\u041b\u0418 \u041a\u041e\u0420\u0410\u0411\u0415\u041b\u042c, \u041f\u0406\u0414\u0420\u0418\u0412 \u041d\u0410\u0424\u0422\u041e\u0411\u0410\u0417\u0418 \u0412 \u0411\u0404\u041b\u0413\u041e\u0420\u041e\u0414\u0406, \u0410\u0412\u0406\u0410\u0411\u041e\u041c\u0411\u0418 \u041d\u0410 \u0425\u0415\u0420\u0421\u041e\u041d\u0429\u0418\u041d\u0406: \u0441\u0442\u0440\u0456\u043c \u0456\u0437 \u043c\u0456\u0441\u0442\u0430 \u043d\u0430 \u0421\u0445\u043e\u0434\u0456\" width=\"640\"></iframe></p><p><em><strong>\u8fd9\u4e9b\u4e3b\u9898\u548c\u5176\u4ed6\u4e3b\u9898\u7531\u6211\u4eec\u7684\u6f14\u8bb2\u8005\u8ba8\u8bba - \u521d\u7ea7\u4e2d\u5c09\u8c22\u5c14\u76d6\u00b7\u5229\u666e\u79d1\uff08Sergey Lipko\uff09\u548c\u4e2d\u6821\u8c22\u5c14\u76d6\u00b7\u7c73\u7d22\u62c9\uff08Sergei Misyura\uff09\u3002</strong></em></p></div>", "source": "https://armyinform.com.ua/2024/03/05/potopyly-korabel-pidryv-naftobazy-v-byelgorodi-aviabomby-na-hersonshhyni-strim-iz-mista-na-shodi/", "title": "\u8fd9\u8258\u8239\u6c89\u6ca1\u4e86\uff0c\u8d1d\u5c14\u6208\u7f57\u5fb7\u7684\u77f3\u6cb9\u4ed3\u5e93\uff0c\u8d6b\u5c14\u68ee\u5730\u533a\u7684\u5b89\u5168\u6c14\u56ca\uff1a\u4e1c\u90e8\u57ce\u5e02\u7684\u661f\u661f", "description": "\u5728Avdiivka\u7684\u90ca\u533a\uff0c\u7b2c\u4e09\u4e2a\u72ec\u7acb\u7684\u7a81\u51fb\u65c5\u7684\u6218\u58eb\u88ab\u4fc4\u7f57\u65af\u4eba\u4fd8\u864f...", "author": ["Army Inform"], "categories": ["\u041d\u043e\u0432\u0438\u043d\u0438"], "tags": ["\u0410\u0440\u043c\u0456\u044f TV", "\u0421\u0442\u0440\u0456\u043c"]}