{"published time": "2024-03-17T22:18:00+08:00", "news source": "https://x.com/MKava0224/status/1769367639950782570", "lng": "35.47286", "lat": "50.51977", "location": ["Belgorod"], "id": 22636255, "action": "airplane-1", "title": "Russian aviation launching guided bombs towards Okhtyrka", "images": [], "content": "<h2>Russian aviation launching guided bombs towards Okhtyrka</h2>\n<div class=\"popup_video\"></div>\n<div class=\"popup_imgi\"></div>", "source": "https://liveuamap.com/en/2024/17-march-russian-aviation-launching-guided-bombs-towards", "author": ["Live UA Map"], "categories": ["Russia"], "tags": ["Belgorod"], "source_name": "LiveUAMap"}