{"published time": "2024-03-23T20:54:00+08:00", "images": ["https://armyinform.com.ua/wp-content/uploads/2024/03/harkiv_udar.jpg", "https://armyinform.com.ua/wp-content/uploads/2024/03/harkiv_udar2.jpg", "https://armyinform.com.ua/wp-content/uploads/2024/03/harkiv_udar3.jpg", "https://armyinform.com.ua/wp-content/uploads/2024/03/harkiv_udar4.jpg"], "content": "<div class=\"single-content\"><figure class=\"post-thumbnail\"><img alt=\"\" class=\"attachment-post-thumbnail size-post-thumbnail wp-post-image\" height=\"833\" src=\"../Images/2024-03-23T20-54-00-08-00/000000.jpg\" srcset=\"../Images/2024-03-23T20-54-00-08-00/000000.jpg\" width=\"1280\"/></figure><!-- .post-thumbnail --><p><strong>On March 23, at about 5:45 pm, the Armed Forces of the Russian Federation struck a missile strike in the Slobid district of Kharkiv.</strong></p><p>About this<a href=\"https://t.me/pgo_gov_ua/22633\" rel=\"nofollow\" target=\"_blank\">reported</a>Office of the Prosecutor General.</p><p>The warehouses and buildings of the enterprise were damaged. The pre -trial investigation into the violation of the laws and customs of war (Part 1 of Article 438 of the Criminal Code of Ukraine) was started.</p><div class=\"fotorama--wp\" data-auto=\"false\" data-captiontag=\"dd\" data-columns=\"0\" data-icontag=\"dt\" data-ids=\"554980,554981,554982\" data-itemtag=\"dl\" data-link=\"file\" data-max-width=\"100%\" data-ratio=\"1.3361169102296\" data-size=\"large\" data-width=\"1280\"><div class=\"gallery galleryid-554978 gallery-columns-0 gallery-size-thumbnail\" id=\"gallery-1\"><dl class=\"gallery-item\"><dt class=\"gallery-icon landscape\"><img alt=\"\" class=\"attachment-thumbnail size-thumbnail\" height=\"150\" loading=\"lazy\" src=\"../Images/2024-03-23T20-54-00-08-00/000001.jpg\" srcset=\"../Images/2024-03-23T20-54-00-08-00/000001.jpg\" width=\"150\"/></dt></dl><dl class=\"gallery-item\"><dt class=\"gallery-icon landscape\"><img alt=\"\" class=\"attachment-thumbnail size-thumbnail\" height=\"150\" loading=\"lazy\" src=\"../Images/2024-03-23T20-54-00-08-00/000002.jpg\" srcset=\"../Images/2024-03-23T20-54-00-08-00/000002.jpg\" width=\"150\"/></dt></dl><dl class=\"gallery-item\"><dt class=\"gallery-icon landscape\"><img alt=\"\" class=\"attachment-thumbnail size-thumbnail\" height=\"150\" loading=\"lazy\" src=\"../Images/2024-03-23T20-54-00-08-00/000003.jpg\" srcset=\"../Images/2024-03-23T20-54-00-08-00/000003.jpg\" width=\"150\"/></dt></dl></div></div><p>Before<a href=\"https://armyinform.com.ua/2024/03/23/vijska-rf-atakuvaly-balistykoyu-odeshhynu/\">The Armyinform reported</a>that the Russian troops attacked the Baltic Studies of Odesa.</p><p></p></div>", "source": "https://armyinform.com.ua/2024/03/23/po-harkovu-udaryly-raketoyu-h-35/", "title": "Kharkov hit the X-35 rocket", "description": "This was reported by the Office of the Prosecutor General. Damaged warehouses and ...", "author": ["Army Inform"], "categories": ["\u041d\u043e\u0432\u0438\u043d\u0438"], "tags": ["\u041e\u0444\u0456\u0441 \u0413\u0435\u043d\u0435\u0440\u0430\u043b\u044c\u043d\u043e\u0433\u043e \u043f\u0440\u043e\u043a\u0443\u0440\u043e\u0440\u0430", "\u0440\u0430\u043a\u0435\u0442\u043d\u0438\u0439 \u0443\u0434\u0430\u0440", "\u0425\u0430\u0440\u043a\u0456\u0432"], "source_name": "ArmyInform"}