{"published time": "2024-03-09T17-12-99", "images": ["https://armyinform.com.ua/wp-content/uploads/2023/05/foto_1-3.jpg"], "content": "<div class=\"single-content\"><figure class=\"post-thumbnail\"><img alt=\"\" class=\"attachment-post-thumbnail size-post-thumbnail wp-post-image\" height=\"800\" src=\"../Images/2024-03-09T17-12-99/000000.jpg\" srcset=\"../Images/2024-03-09T17-12-99/000000.jpg\" width=\"1200\"/><figcaption class=\"wp-caption-text\">MBDA Taurus AM AM Eurofighter\uff0cManching</figcaption></figure><!-- .post-thumbnail --><p><strong>\u82f1\u56fd\u63d0\u51fa\u4e86\u4e00\u79cd\u89e3\u51b3\u65b9\u6848\uff0c\u8be5\u89e3\u51b3\u65b9\u6848\u5c06\u589e\u52a0\u5411\u4e4c\u514b\u5170\u7684\u957f\u8ddd\u79bb\u5de1\u822a\u5bfc\u5f39\u7684\u4f9b\u5e94\u3002</strong></p><p>\u8fd9\u8bf4\u660e\u4e86<a href=\"https://www.sueddeutsche.de/projekte/artikel/politik/david-cameron-interview-nato-ukraine-taurus-scholz-usa-trump-israel-e095522/?reduced=true\" rel=\"nofollow\" target=\"_blank\">Southgerman\u62a5\u7eb8</a>\u3002</p><p>\u8fd9\u4f4d\u90e8\u957f\u5efa\u8bae\u5fb7\u56fd\u53ef\u4ee5\u5728\u82f1\u56fd\u653e\u7f6e\u91d1\u725b\u5ea7\u5bfc\u5f39\uff0c\u800c\u4f26\u6566\u5c06\u4e3a\u4e4c\u514b\u5170\u63d0\u4f9b\u5b9e\u9645\u4e0a\u662f\u5176\u4ed6\u98ce\u66b4\u5f71\u5bfc\u5f39<a href=\"https://armyinform.com.ua/2023/05/25/krylata-raketa-taurus-kepd-dostojnyj-konkurent-brytanskoyi-storm-shadow/\">\u5fb7\u56fd\u706b\u7bad\u7684\u7c7b\u4f3c\u7269</a>\u3002</p><p>\u6234\u7ef4\u00b7\u5361\u6885\u4f26\uff08David Cameron\uff09\u8bf4\uff1a\u201c\u6211\u4eec\u51b3\u5fc3\u4e0e\u5fb7\u56fd\u5408\u4f5c\u4f19\u4f34\u7d27\u5bc6\u5408\u4f5c\uff0c\u8ba8\u8bba\u8fd9\u548c\u6240\u6709\u5176\u4ed6\u95ee\u9898\uff0c\u4ee5\u5e2e\u52a9\u4e4c\u514b\u5170\u3002\u201d</p><p>\u82f1\u56fd\u5916\u4ea4\u5927\u81e3\u8fd8\u62d2\u7edd\u62c5\u5fc3\u957f\u671f\u5bfc\u5f39\u7684\u4f9b\u5e94\u4f1a\u5bfc\u81f4\u4e4c\u514b\u5170\u6218\u4e89\u7684\u5347\u7ea7\u3002</p><p>\u4ed6\u89e3\u91ca\u8bf4\uff1a\u201c\u5f88\u6709\u53ef\u80fd\u5bf9\u4f7f\u7528\u8fd9\u4e9b\u6b66\u5668\u65bd\u52a0\u9650\u5236\uff0c\u4ee5\u786e\u4fdd\u5b83\u7edd\u4e0d\u4f1a\u4fc3\u8fdb\u5347\u7ea7\u3002\u201d</p><p>2\u6708\uff0c\u5fb7\u56fd\u8054\u90a6\u653f\u5e9c\u6295\u7968\u901a\u8fc7\u63a8\u8350\u7ed9\u4e4c\u514b\u5170\u63d0\u4f9b\u957f\u671f\u6b66\u5668\u3002 \u4f46\u662f\uff0c\u5fb7\u56fd\u603b\u7406\u5965\u62c9\u592b\u00b7\u8212\u5c14\u8328\uff08Olaf Scholtz\uff09\u53cd\u5bf9\u8fd9\u4e9b\u5bfc\u5f39\u7684\u8f6c\u79fb\u3002 \u4ed6\u8ba4\u4e3a\uff0c\u8fd9\u6837\u7684\u6b65\u9aa4\u53ef\u4ee5\u4f7f\u5fb7\u56fd\u4e0e\u4fc4\u7f57\u65af\u76f4\u63a5\u51b2\u7a81\u3002</p><p>\u636e\u5fb7\u56fd\u653f\u5e9c\u62a5\u9053<a href=\"https://armyinform.com.ua/2024/02/27/nimechchyna-nadala-novyj-paket-dopomogy-14-tysyach-snaryadiv-i-mashyny-rozminuvannya/\">\u5ba3\u5e03</a>\u5173\u4e8e\u4e0b\u4e00\u4e2a\u519b\u4e8b\u63f4\u52a9\u515a\u524d\u5f80\u4e4c\u514b\u5170\u7684\u79bb\u5f00\uff0c\u5176\u4e2d\u5305\u62ec155\u6beb\u7c73\u53e3\u5f84\u768414,000\u679a\u70ae\u5f39\u3002</p></div>", "source": "https://armyinform.com.ua/2024/03/09/velyka-brytaniya-zaproponuvala-nimechchyni-variant-postavok-ukrayini-dalekobijnyh-raket/", "title": "\u82f1\u56fd\u4e3a\u5fb7\u56fd\u63d0\u4f9b\u4e86\u4e4c\u514b\u5170\u957f\u671f\u5bfc\u5f39\u7684\u5404\u79cd\u7528\u54c1", "description": "\u82f1\u56fd\u5916\u4ea4\u90e8\u957f\u8a79\u59c6\u65af\u00b7\u5361\u6885\u4f26\uff08James Cameron\uff09\u5728\u63a5\u53d7\u91c7\u8bbf\u65f6\u8bf4\u660e\u4e86\u8fd9\u4e00\u70b9...", "author": ["Army Inform"], "categories": ["\u041d\u043e\u0432\u0438\u043d\u0438"], "tags": ["\u0412\u0435\u043b\u0438\u043a\u0430 \u0411\u0440\u0438\u0442\u0430\u043d\u0456\u044f", "\u0434\u043e\u043f\u043e\u043c\u043e\u0433\u0430 \u043f\u0430\u0440\u0442\u043d\u0435\u0440\u0456\u0432", "\u041d\u0456\u043c\u0435\u0447\u0447\u0438\u043d\u0430"]}