{"published time": "2024-03-06T22-39-00", "news source": "https://t.me/dneproperatyv/90331", "lng": "34.37777", "lat": "47.58199", "location": ["Zaporizhia"], "id": 22633860, "action": "bomb-1", "title": "Big fire in Nikopol after Russian shelling", "images": ["https://liveuamap.com/pics/2024/03/06/22633860_1.jpg", "https://liveuamap.com/pics/2024/03/06/22633860_2.jpg"], "content": "<h2>Big fire in Nikopol after Russian shelling</h2><div class=\"popup_video\"><label><iframe allowfullscreen=\"\" frameborder=\"0\" height=\"337\" mozallowfullscreen=\"\" src=\"https://player.vimeo.com/video/https://t.me/dneproperatyv/90331?embed=1embed/simple\" webkitallowfullscreen=\"\" width=\"600\"></iframe></label></div><label><img alt=\"Big fire in Nikopol after Russian shelling\" src=\"../Images/2024-03-06T22-39-00/000000.jpg\" srcset=\"../Images/2024-03-06T22-39-00/000000.jpg\"/></label><div class=\"popup_imgi\"><img alt=\"Big fire in Nikopol after Russian shelling\" src=\"../Images/2024-03-06T22-39-00/000001.jpg\" srcset=\"../Images/2024-03-06T22-39-00/000001.jpg\"/></div>", "source": "https://liveuamap.com/en/2024/6-march-big-fire-in-nikopol-after-russian-shelling", "author": ["Live UA Map"], "categories": [], "tags": ["Zaporizhia"]}