{"published time": "2024-03-06T07-21-99", "images": ["https://armyinform.com.ua/wp-content/uploads/2024/03/91bbb7ef-8cf8-4736-acab-105435f7d4fa.jpeg"], "content": "<div class=\"single-content\"><figure class=\"post-thumbnail\"><img alt=\"\" class=\"attachment-post-thumbnail size-post-thumbnail wp-post-image\" height=\"850\" sizes=\"(max-width: 1134px) 100vw, 1134px\" src=\"../Images/2024-03-06T07-21-99/000000.jpeg\" srcset=\"../Images/2024-03-06T07-21-99/000000.jpeg\" width=\"1134\"/></figure><!-- .post-thumbnail --><p><strong>During the last day, the Russian Federation has inflicted 328 beats in 6 cities and villages of Zaporizhzhya region.</strong></p><p>About this<a href=\"https://t.me/ivan_fedorov_zp/5141\" rel=\"nofollow\" target=\"_blank\">reported</a>Head of Zaporizhzhya Ova Ivan Fedorov.</p><p>The Russian servicemen hit 7 air shells on Malinovka, Guliaypole and a small toct.</p><p>The occupiers also made 21 RSZV-weapons Malinovka, small Tokmachka and robot, and attacked 59 drones of Gulyaypole, Novodanilovka, Levadne, robot, small Tokmachka and Malynivka.</p><p>In addition, 241 artillery blow came across the territory of Guliaypol, Robovy, Malynivka, Little Tokmachka, Novodanylivka and Levadny.</p><p>There were 11 reports of destruction of residential buildings and infrastructure. The civilians were not injured.</p><p>As reported by the Armyinform, tonight Russian troops<a href=\"https://armyinform.com.ua/2024/03/06/u-sumah-ye-vluchannya-vnaslidok-nichnoyi-ataky-shahediv/\">attacked</a>The city of Sumy Sumy -type drones is a hit.</p></div>", "source": "https://armyinform.com.ua/2024/03/06/u-zaporizkij-oblasti-okupanty-zavdaly-328-udariv-za-dobu/", "title": "In the Zaporozhye region, the occupiers made 328 beats per day", "description": "The head of Zaporizhzhya Ova Ivan Fedorov informed about it. RF soldiers hit 7 ...", "author": ["Army Inform"], "categories": ["\u041d\u043e\u0432\u0438\u043d\u0438"], "tags": ["\u0432\u043e\u0440\u043e\u0436\u0456 \u043e\u0431\u0441\u0442\u0440\u0456\u043b\u0438", "\u0417\u0430\u043f\u043e\u0440\u0456\u0437\u044c\u043a\u0430 \u043e\u0431\u043b\u0430\u0441\u0442\u044c"]}