{"published time": "2024-03-12T23:06:00+08:00", "news source": "https://x.com/SkyNewsArabia_B/status/1767567823272878575", "lng": "37.58663", "lat": "55.74482", "location": ["Moskva", "Moscow"], "id": 22635116, "action": "speech-1", "title": "\u4fc4\u7f57\u65af\u5916\u4ea4\u90e8\uff1a\u4e4c\u514b\u5170\u5fc5\u987b\u53d6\u6d88\u963b\u6b62\u4e0e\u4fc4\u7f57\u65af\u8c08\u5224\u7684\u6cd5\u5f8b", "images": [], "content": "<h2>\u4fc4\u7f57\u65af\u5916\u4ea4\u90e8\uff1a\u4e4c\u514b\u5170\u5fc5\u987b\u53d6\u6d88\u963b\u6b62\u4e0e\u4fc4\u7f57\u65af\u8c08\u5224\u7684\u6cd5\u5f8b</h2><div class=\"popup_video\"></div><div class=\"popup_imgi\"></div>", "source": "https://liveuamap.com/en/2024/12-march-russian-foreign-ministry-ukraine-must-lift-the-law", "author": ["Live UA Map"], "categories": ["Russia"], "tags": ["Moskva", "Moscow"], "source_name": "LiveUAMap"}