{"published time": "2024-03-26T07:36:00+08:00", "images": ["https://armyinform.com.ua/wp-content/uploads/2023/12/shahedy-scaled.jpg"], "content": "<div class=\"single-content\"><figure class=\"post-thumbnail\"><img alt=\"\" class=\"attachment-post-thumbnail size-post-thumbnail wp-post-image\" height=\"675\" sizes=\"(max-width: 1200px) 100vw, 1200px\" src=\"../Images/2024-03-26T07-36-00-08-00/000000.jpg\" srcset=\"../Images/2024-03-26T07-36-00-08-00/000000.jpg\" width=\"1200\"/><figcaption class=\"wp-caption-text\">Illustrative photo</figcaption></figure><!-- .post-thumbnail --><p><strong>On the night of March 26, the Russians attacked Ukraine with 12 shock drones such as Shahd, all enemy drones were destroyed.</strong></p><p>About this<a href=\"https://t.me/ComAFUA/243\" rel=\"nofollow\" target=\"_blank\">reported</a>Air Force Commander Lieutenant General Mykola Oleshchuk.</p><p>\"The enemy attacked 12 shaped UAVs from Chauda-Crimea and Kursk region-the Russian Federation, as well as two anti-aircraft guided missiles C-300 towards Donetsk region,\" he said.</p><p>According to the commander, the air attack reflects the mobile fire groups of defense forces of Ukraine in the Nikolaev and Kharkiv regions.</p><p>\"All 12\" Shahmed \"was shot. Thank you for your successful combat work! Together to victory!\" -said Lieutenant General Mykola Oleshchuk.</p><p>As reported<a href=\"https://armyinform.com.ua/2024/03/25/na-pivdni-ppo-znyshhyla-8-udarnyh-bpla-typu-shahed/\">Armyinform</a>, over the last day, the air defense has destroyed 8 shock UAVs in the south.</p></div>", "source": "https://armyinform.com.ua/2024/03/26/povitryani-syly-zbyly-usi-12-shahediv-yakymy-rosiya-atakuvala-ukrayinu/", "title": "Air Force knocked down all 12 \"Shahmed\" that Russia attacked Ukraine", "description": "This was reported by the Commander of the Air Force Lieutenant General Mykola Oleshchuk. \"Enemy...", "author": ["Army Inform"], "categories": ["\u041d\u043e\u0432\u0438\u043d\u0438"], "tags": ["stoprussia", "\u0430\u0433\u0440\u0435\u0441\u0456\u044f \u0440\u0444", "\u0432\u0442\u043e\u0440\u0433\u043d\u0435\u043d\u043d\u044f \u0440\u0444", "\u0432\u0442\u0440\u0430\u0442\u0438 \u0432\u043e\u0440\u043e\u0433\u0430"], "source_name": "ArmyInform"}