{"published time": "2024-03-26T18:12:00+08:00", "images": ["https://armyinform.com.ua/wp-content/uploads/2024/03/dpsu_udar.png"], "content": "<div class=\"single-content\"><figure class=\"post-thumbnail\"><img alt=\"\" class=\"attachment-post-thumbnail size-post-thumbnail wp-post-image\" height=\"1014\" sizes=\"(max-width: 1920px) 100vw, 1920px\" src=\"../Images/2024-03-26T18-12-00-08-00/000000.png\" srcset=\"../Images/2024-03-26T18-12-00-08-00/000000.png\" width=\"1920\"/></figure><!-- .post-thumbnail --><p><strong>In the Bakhmut direction, an enemy BTR-82A and three shelters of the occupiers were eliminated with the help of attack UAVs.</strong></p><p>Relevant Video<a href=\"https://t.me/DPSUkr/19103\" rel=\"nofollow\" target=\"_blank\">She posted on March 26</a>State Border Service of Ukraine.</p><p><iframe allowfullscreen=\"allowfullscreen\" frameborder=\"0\" height=\"314\" loading=\"lazy\" scrolling=\"no\" src=\"https://www.facebook.com/plugins/video.php?height=314&amp;href=https%3A%2F%2Fwww.facebook.com%2FDPSUkraine%2Fvideos%2F807754328049873%2F&amp;show_text=false&amp;width=560&amp;t=0\" style=\"border: none; overflow: hidden;\" width=\"560\"></iframe></p><p>The strike was carried out by border guards of the Revenge Offensive Guard brigade.</p><p>\u042f\u043a<a href=\"https://armyinform.com.ua/2024/03/26/u-dnipropetrovskij-oblasti-zbyly-vorozhu-raketu-h-59/\">The ArmyInform reported earlier</a>, an enemy Kh-59 missile was shot down in the Dnipropetrovsk region.</p></div>", "source": "https://armyinform.com.ua/2024/03/26/syly-oborony-znyshhyly-try-ukryttya-i-bronetehniku-voroga/", "title": "Defense forces destroyed three shelters and armored vehicles of an enemy", "description": "The relevant video was posted on March 26 by the State Border Service of Ukraine. Blow ...", "author": ["Army Inform"], "categories": ["\u041d\u043e\u0432\u0438\u043d\u0438"], "tags": ["\u0432\u0442\u0440\u0430\u0442\u0438 \u0432\u043e\u0440\u043e\u0433\u0430", "\u0414\u041f\u0421\u0423", "\u041f\u043e\u043c\u0441\u0442\u0430", "\u0425\u0440\u043e\u043d\u0456\u043a\u0430 \u0432\u0456\u0439\u043d\u0438"], "source_name": "ArmyInform"}