{"published time": "2024-11-19T18:36:00+08:00", "images": ["https://armyinform.com.ua/wp-content/uploads/2024/11/dpsu_poryatunok-raketnykiv.png"], "content": "<div class=\"single-content\"><figure class=\"post-thumbnail\"><img alt=\"\" class=\"attachment-post-thumbnail size-post-thumbnail wp-post-image\" height=\"975\" sizes=\"(max-width: 1920px) 100vw, 1920px\" src=\"../Images/2024-11-19T18-36-00-08-00/000000.png\" srcset=\"../Images/2024-11-19T18-36-00-08-00/000000.png\" width=\"1920\"/><figcaption class=\"wp-caption-text\">\u4fc4\u7f57\u65af\u65e0\u4eba\u673a\u6444\u50cf\u673a\u7684\u6846\u67b6\uff0c\u654c\u4eba\u8ba4\u4e3a\u8fd9\u662f\u6bc1\u706d\u76ee\u6807\u7684\u8bc1\u660e\u3002 \u5f92\u7136\u3002</figcaption></figure><!-- .post-thumbnail --><p><strong>RAK-SA-12\u53cd\u5e94\u88c5\u7f6e\u4e0d\u4ec5\u80fd\u591f\u5728\u654c\u5bf9\u65e0\u4eba\u673a\u540e\u751f\u5b58\uff0c\u800c\u4e14\u8fd8\u53ef\u4ee5\u5728\u89c6\u9891\u4e2d\u62cd\u6444\u3002</strong></p><p>\u6218\u6597\u5de5\u4f5c\u548c\u975e\u5e73\u51e1\u6551\u63f4\u7684\u955c\u5934<a href=\"https://youtu.be/rlwo-U_huWk\" rel=\"nofollow\" target=\"_blank\">\u5979\u516c\u5f00</a>\u4e4c\u514b\u5170\u56fd\u5bb6\u8fb9\u5883\u670d\u52a1\u3002</p><p>\u51e0\u5929\u524d\uff0c\u4fc4\u7f57\u65af\u7684\u5ba3\u4f20\u8005\u5f00\u59cb\u5439\u5618\u6211\u4eecRAK-SA-12\u88c5\u7f6e\u7684FPV\u6307\u6807\u7684\u5370\u8c61\uff0c\u8be5\u88c5\u7f6e\u5b89\u88c5\u5728\u88c5\u7532\u8f66\u201c Khamvi\u201d\u4e0a\u3002 \u5165\u4fb5\u8005\u5439\u5618\u4ed6\u4eec\u4e0d\u4ec5\u6467\u6bc1\u4e86\u6c7d\u8f66\uff0c\u800c\u4e14\u6467\u6bc1\u4e86\u6574\u4e2a\u8239\u5458\u3002</p><p>\u4f46\u4e8b\u5b9e\u8bc1\u660e\uff0c\u4fc4\u7f57\u65af\u4eba\u6492\u8c0e\u3002 \u7167\u5e38\u3002</p><p>\u6211\u4eec\u7684\u706b\u7bad\u53d1\u5c04\u5668\u8bb2\u8ff0\u4e86\u4ed6\u4eec\u4ee4\u4eba\u60ca\u53f9\u7684\u6551\u63f4\u7684\u6545\u4e8b\uff0c\u5f53\u65f6\u4ed6\u4eec\u4e0d\u4ec5\u5e78\u514d\u4e8e\u96be\uff0c\u800c\u4e14\u5728\u4ed6\u4eec\u7684\u6280\u672f\u4e2d\u5e78\u5b58\u4e0b\u6765\uff0c\u8fd9\u5728\u4fc4\u7f57\u65af\u4eba\u4e2d\u5f97\u5230\u4e86\u6781\u5927\u7684\u53cd\u6620\u3002</p><p>\u5982\u4f55\u770b\u5f85\u4fc4\u7f57\u65afFPV-Drone\u7684\u89c6\u9891 - \u89c2\u770b\u89c6\u9891\uff1a</p><p><iframe allowfullscreen=\"allowfullscreen\" frameborder=\"0\" height=\"480\" loading=\"lazy\" src=\"https://www.youtube.com/embed/rlwo-U_huWk\" title=\"\u0420\u043e\u0441\u0456\u0439\u0441\u044c\u043a\u0438\u0439 FPV-\u0434\u0440\u043e\u043d \u0430\u0442\u0430\u043a\u0443\u0432\u0430\u0432 \u0420\u0421\u0417\u0412 \u043f\u0440\u0438\u043a\u043e\u0440\u0434\u043e\u043d\u043d\u0438\u043a\u0456\u0432: \u043a\u0430\u0434\u0440\u0438 \u0437 \u043a\u0443\u0437\u043e\u0432\u0430 \u043c\u0430\u0448\u0438\u043d\u0438\" width=\"1263\"></iframe></p><p>\u519b\u961f\u544a\u8bc9RSZV RAK\u5982\u4f55<a href=\"https://armyinform.com.ua/2024/10/15/desyatky-zagyblyh-ta-poranenyh-okupantiv-yak-rszv-rak-znyshhuye-vorozhu-pihotu/\">\u6467\u6bc1\u654c\u5bf9\u7684\u6b65\u5175</a>\u3002</p></div>", "source": "https://armyinform.com.ua/2024/11/19/zbrehavshy-rosijski-propagandysty-pohovaly-nashyh-raketnykiv-a-ti-vryatuvalysya/", "title": "\u6492\u8c0e - \u4fc4\u7f57\u65af\u5ba3\u4f20\u5bb6\u201c\u57cb\u846c\u201d\u4e86\u6211\u4eec\u7684\u706b\u7bad\u53d1\u5c04\u5668\uff0c\u4ed6\u4eec\u4fdd\u5b58\u4e86", "description": "\u6218\u6597\u5de5\u4f5c\u4eba\u5458\u548c\u975e\u5e73\u51e1\u7684\u6551\u8d4e\u8005\u7531\u5dde\u8fb9\u5883\u670d\u52a1\u90e8\u95e8\u51fa\u7248...", "author": ["Army Inform"], "categories": ["\u0412\u0456\u0434\u0435\u043e", "\u041d\u043e\u0432\u0438\u043d\u0438"], "tags": ["\u0414\u041f\u0421\u0423"], "source_name": "ArmyInform"}