{"published time": "2024-03-12T16:22:00+08:00", "news source": "https://t.me/rian_ru/234918", "lng": "34.28784", "lat": "51.26574", "location": ["Kursk"], "id": 22635036, "action": "ak-1", "title": "Governor of Kursk regions says infiltration attempt in Tyotkino was foiled", "images": [], "content": "<h2>Governor of Kursk regions says infiltration attempt in Tyotkino was foiled</h2><div class=\"popup_video\"></div><div class=\"popup_imgi\"></div>", "source": "https://liveuamap.com/en/2024/12-march-governor-of-kursk-regions-says-infiltration-attempt", "author": ["Live UA Map"], "categories": ["Russia"], "tags": ["Kursk"], "source_name": "LiveUAMap"}