{"published time": "2024-11-16T17:32:00+08:00", "images": ["https://armyinform.com.ua/wp-content/uploads/2024/11/stream_packshot_kupyansk.png"], "content": "<div class=\"single-content\"><figure class=\"post-thumbnail\"><img alt=\"\" class=\"attachment-post-thumbnail size-post-thumbnail wp-post-image\" height=\"720\" sizes=\"(max-width: 1280px) 100vw, 1280px\" src=\"../Images/2024-11-16T17-32-00-08-00/000000.png\" srcset=\"../Images/2024-11-16T17-32-00-08-00/000000.png\" width=\"1280\"/></figure><!-- .post-thumbnail --><p><strong>SCO\u6218\u6597\u4eba\u5458\u64a4\u79bb\u4e86\u5e93\u4ec0\u57fa\u7eb3\u4e4c\u514b\u5170\u768416\u540d\u519b\u4e8b\u56fd\u9632\u519b\u3002</strong></p><p>\u5728\u7b2c\u4e8c\u5929\u665a\u4e0a\uff0c73\u6d77\u4e8b\u4e2d\u5fc3\u7684\u8fd0\u8425\u5546\u5e94\u4e3a\u4e00\u9879\u6218\u6597\u4efb\u52a1\uff0c\u4ee5\u4ece\u53cb\u597d\u7684\u90e8\u961f\u4e2d\u64a4\u51fa\u4e00\u7ec4\u519b\u4eba\u3002 \u8be5\u758f\u6563\u7ec4\u7ec7\u5728\u654c\u65b9\u5766\u514b\uff0c\u673a\u67aa\u706b\u548cFPV  - \u89e6\u53ca\u6469\u6258\u7684\u706b\u707e\u4e0b\u5de5\u4f5c\u3002</p><p>Khorne\u96c6\u56e2\u8fd0\u8425\u5546\u5c55\u793a\u4e86Kupyanskaya\u6846\u67b6\u3002 \u4fc4\u7f57\u65af\u4eba\u95ef\u5165\u8fd9\u5ea7\u57ce\u5e02\u540e\uff0c\u6211\u4eec\u7684\u6218\u58eb\u6dd8\u6c70\u4e86\u4ed6\u4eec\u3002 \u89c6\u9891\u663e\u793a\u5360\u9886\u8005\u7684\u624b\u81c2\u88ab\u6211\u4eec\u7684\u519b\u961f\u6293\u83b7\u3002</p><p>SBU\u7279\u79cd\u90e8\u961f\u6467\u6bc1\u4e86\u8bd5\u56fe\u88ad\u51fb\u7684\u4fc4\u7f57\u65af\u4eba\u3002 SBU\u7684CSU\u201c A\u201d\u7684FPV-Droons\u751a\u81f3\u5728\u88ad\u51fb\u53cb\u597d\u5355\u4f4d\u7684\u4f4d\u7f6e\u4e4b\u524d\u5c31\u963b\u6b62\u4e86\u654c\u5bf9\u6b65\u5175\u3002</p><p>\u8fd9\u4e9b\u4e3b\u9898\u548c\u5176\u4ed6\u4e3b\u9898\u7531\u6211\u4eec\u7684\u4e3b\u6301\u4ebaArtem Golub\u548cAndrey Makarenko\u5c11\u6821\u8ba8\u8bba\u3002</p><p><iframe allowfullscreen=\"allowfullscreen\" frameborder=\"0\" height=\"315\" loading=\"lazy\" src=\"https://www.youtube.com/embed/QLsAzKR4HW4?si=4QN9W0q1n_t2d36G\" title=\"YouTube video player\" width=\"560\"></iframe></p></div>", "source": "https://armyinform.com.ua/2024/11/16/madyar-robyt-feyerverk-z-rosiyan-sbu-likviduye-okupantiv-operacziya-sso-strim-iz-pryfrontovogo-mista/", "title": "Magyar\u4ece\u4fc4\u7f57\u65af\u4eba\u5236\u4f5c\u70df\u82b1\uff0cSBU\u6d88\u9664\u4e86\u5360\u9886\u8005\uff0cSCO\u624b\u672f\uff1a\u6765\u81ea\u8fb9\u5883\u57ce\u5e02\u7684\u660e\u661f", "description": "\u7b2c\u4e8c\u5929\u665a\u4e0a\uff0c73\u6d77\u4e8b\u4e2d\u5fc3\u7684\u8fd0\u8425\u5546\u63a5\u5230\u4e86\u73af\u5883\u7684\u6218\u6597\u4efb\u52a1...", "author": ["Army Inform"], "categories": ["\u041d\u043e\u0432\u0438\u043d\u0438"], "tags": ["\u0410\u0440\u043c\u0456\u044f TV"], "source_name": "ArmyInform"}