{"published time": "2024-03-21T16:50:00+08:00", "news source": "https://t.me/astrapress/51716", "lng": "35.69092", "lat": "50.47329", "location": ["Grayvoron"], "id": 22637161, "action": "rescue-1", "title": "Belgorod\u5730\u533aGrayvoron\u7684\u5f53\u5c40\u8981\u6c42\u516c\u6c11\u64a4\u79bbYaroslavl\u5730\u533a", "images": [], "content": "<h2>Belgorod\u5730\u533aGrayvoron\u7684\u5f53\u5c40\u8981\u6c42\u516c\u6c11\u64a4\u79bbYaroslavl\u5730\u533a</h2><div class=\"popup_video\"></div><div class=\"popup_imgi\"></div>", "source": "https://liveuamap.com/en/2024/21-march-authorities-in-grayvoron-of-belgorod-region-asking", "author": ["Live UA Map"], "categories": ["Russia"], "tags": ["Grayvoron"], "source_name": "LiveUAMap"}