{"published time": "2024-03-28T16:43:00+08:00", "images": ["https://armyinform.com.ua/wp-content/uploads/2024/03/photo1711634628-4.jpeg", "https://armyinform.com.ua/wp-content/uploads/2024/03/photo1711634628-3.jpeg", "https://armyinform.com.ua/wp-content/uploads/2024/03/photo1711634628-2.jpeg", "https://armyinform.com.ua/wp-content/uploads/2024/03/photo1711634628.jpeg", "https://armyinform.com.ua/wp-content/uploads/2024/03/photo1711634628-1.jpeg"], "content": "<div class=\"single-content\"><figure class=\"post-thumbnail\"><img alt=\"\" class=\"attachment-post-thumbnail size-post-thumbnail wp-post-image\" height=\"853\" src=\"../Images/2024-03-28T16-43-00-08-00/000000.jpeg\" srcset=\"../Images/2024-03-28T16-43-00-08-00/000000.jpeg\" width=\"1280\"/></figure><!-- .post-thumbnail --><p><strong>Ivan Fedorov showed the mutilated houses of the private sector of Zaporozhye after today's Russian attack.</strong></p><p>About this<a href=\"https://t.me/ivan_fedorov_zp/5878\" rel=\"nofollow\" target=\"_blank\">head</a>Zaporizhzhya Ova wrote in his telegram channel.</p><p>According to Ivan Fedorov, over the last week the enemy has been hunted on houses and facilities of infrastructure of Zaporizhzhya region more than 2000 times.</p><div class=\"fotorama--wp\" data-auto=\"false\" data-captiontag=\"dd\" data-columns=\"0\" data-icontag=\"dt\" data-ids=\"558774,558775,558777,558776\" data-itemtag=\"dl\" data-link=\"file\" data-max-width=\"100%\" data-ratio=\"1.5005861664713\" data-size=\"large\" data-width=\"1280\"><div class=\"gallery galleryid-558771 gallery-columns-0 gallery-size-thumbnail\" id=\"gallery-1\"><dl class=\"gallery-item\"><dt class=\"gallery-icon landscape\"><img alt=\"\" class=\"attachment-thumbnail size-thumbnail\" height=\"150\" loading=\"lazy\" src=\"../Images/2024-03-28T16-43-00-08-00/000001.jpeg\" srcset=\"../Images/2024-03-28T16-43-00-08-00/000001.jpeg\" width=\"150\"/></dt></dl><dl class=\"gallery-item\"><dt class=\"gallery-icon landscape\"><img alt=\"\" class=\"attachment-thumbnail size-thumbnail\" height=\"150\" loading=\"lazy\" src=\"../Images/2024-03-28T16-43-00-08-00/000002.jpeg\" srcset=\"../Images/2024-03-28T16-43-00-08-00/000002.jpeg\" width=\"150\"/></dt></dl><dl class=\"gallery-item\"><dt class=\"gallery-icon landscape\"><img alt=\"\" class=\"attachment-thumbnail size-thumbnail\" height=\"150\" loading=\"lazy\" src=\"../Images/2024-03-28T16-43-00-08-00/000003.jpeg\" srcset=\"../Images/2024-03-28T16-43-00-08-00/000003.jpeg\" width=\"150\"/></dt></dl><dl class=\"gallery-item\"><dt class=\"gallery-icon landscape\"><img alt=\"\" class=\"attachment-thumbnail size-thumbnail\" height=\"150\" loading=\"lazy\" src=\"../Images/2024-03-28T16-43-00-08-00/000004.jpeg\" srcset=\"../Images/2024-03-28T16-43-00-08-00/000004.jpeg\" width=\"150\"/></dt></dl></div></div><p>\u201cTwo people have been injured today. In total, nearly 1380 civilians have been injured since the beginning of a large -scale invasion, \u201dthe head of the Ova said.</p><p>As reported by the Armyinform, in Zaporozhye as a result of a night attack<a href=\"https://armyinform.com.ua/2024/03/28/u-zaporizhzhi-vnaslidok-nichnoyi-ataky-poraneno-dvoh-zhinok/\">wounded</a>two women.</p></div>", "source": "https://armyinform.com.ua/2024/03/28/vorog-ponad-dvi-tysyachi-raziv-obstrilyav-zaporizhzhya-za-ostannij-tyzhden-ova/", "title": "The enemy has fired at Zaporozhye over two thousand times in the last week - Ova", "description": "The head of Zaporizhzhya Ova wrote about it in his telegram channel. As Ivan said ...", "author": ["Army Inform"], "categories": ["\u041d\u043e\u0432\u0438\u043d\u0438"], "tags": ["stoprussia", "\u0430\u0433\u0440\u0435\u0441\u0456\u044f \u0440\u0444", "\u0432\u0456\u0439\u043d\u0430", "\u0432\u043e\u0440\u043e\u0436\u0456 \u043e\u0431\u0441\u0442\u0440\u0456\u043b\u0438", "\u0432\u0442\u043e\u0440\u0433\u043d\u0435\u043d\u043d\u044f \u0440\u0444", "\u0406\u0432\u0430\u043d \u0424\u0435\u0434\u043e\u0440\u043e\u0432"], "source_name": "ArmyInform"}