{"published time": "2024-03-26T17:04:00+08:00", "images": ["https://armyinform.com.ua/wp-content/uploads/2024/03/uhylyant-v-richczi.png"], "content": "<div class=\"single-content\"><figure class=\"post-thumbnail\"><img alt=\"\" class=\"attachment-post-thumbnail size-post-thumbnail wp-post-image\" height=\"649\" src=\"../Images/2024-03-26T17-04-00-08-00/000000.png\" srcset=\"../Images/2024-03-26T17-04-00-08-00/000000.png\" width=\"1173\"/></figure><!-- .post-thumbnail --><p><strong>\u5728Turunchuk\u6cb3\u4e2d\uff0c22\u5c81\u7684\u6556\u5fb7\u8428\u88ab\u56f0\uff0c\u8ba1\u5212\u975e\u6cd5\u5c06\u8fb9\u754c\u79fb\u81f3\u6469\u5c14\u591a\u74e6\u3002</strong></p><p>\u5bf9\u8fd9\u4e2a<a href=\"https://t.me/DPSUkr/19101\" rel=\"nofollow\" target=\"_blank\">\u5979\u62a5\u90533\u670826\u65e5</a>\u4e4c\u514b\u5170\u56fd\u5bb6\u8fb9\u5883\u670d\u52a1\u3002</p><p>\u6839\u636e\u8fb9\u5883\u8b66\u536b\u7684\u8bf4\u6cd5\uff0c\u4e00\u4f4d\u5f53\u5730\u5c45\u6c11\u63d0\u4f9b\u4e86\u6709\u5173\u4e00\u4e2a\u65e0\u6cd5\u6446\u8131Turunchuk\u6cb3\u6d41\u6c34\u7684\u4eba\u7684\u4fe1\u606f\u3002</p><p>\u514b\u670d\u4e86\u67f3\u6811\u548c\u82a6\u82c7\u540e\uff0c\u8fb9\u9632\u90e8\u961f\u8bbe\u6cd5\u5e2e\u52a9\u4e86\u8fd9\u5bb6\u4f19\u3002 \u533b\u751f\u8bf4\u4e86\u4e25\u91cd\u7684\u4f53\u6e29\u8fc7\u4f4e\u548c\u51bb\u4f24\u7684\u53d7\u5bb3\u8005\u3002</p><p><iframe allow=\"accelerometer; autoplay; clipboard-write; encrypted-media; gyroscope; picture-in-picture; web-share\" allowfullscreen=\"\" frameborder=\"0\" height=\"360\" loading=\"lazy\" src=\"https://www.youtube.com/embed/LtTfWD3dkA4?feature=oembed\" title=\"\u041f\u0440\u0438\u043a\u043e\u0440\u0434\u043e\u043d\u043d\u0438\u043a\u0438 \u0411\u0456\u043b\u0433\u043e\u0440\u043e\u0434-\u0414\u043d\u0456\u0441\u0442\u0440\u043e\u0432\u0441\u044c\u043a\u043e\u0433\u043e \u0437\u0430\u0433\u043e\u043d\u0443 \u0432\u0440\u044f\u0442\u0443\u0432\u0430\u043b\u0438 \u0445\u043b\u043e\u043f\u0446\u044f, \u044f\u043a\u0438\u0439 \u043b\u0435\u0434\u044c \u043d\u0435 \u0437\u0430\u043c\u0435\u0440\u0437 \u0443 \u0440\u0456\u0447\u0446\u0456 \u0422\u0443\u0440\u0443\u043d\u0447\u0443\u043a\" width=\"640\"></iframe></p><p>\u540e\u6765\u900f\u9732\uff0c\u5728Turunchuk\u4e4b\u540e\uff0c\u8fd9\u5bb6\u4f19\u8fd8\u8ba1\u5212\u514b\u670d\u66f4\u9ad8\u6c34\u7684Dniester\u3002 \u663e\u7136\uff0c\u8fd9\u4f4dvidenceman\u7684\u5730\u7406\u6559\u5b66\u5f88\u5dee\u3002</p><p>\u4f5c\u4e3a<a href=\"https://armyinform.com.ua/2024/03/26/na-zakarpatti-zupynyly-dvi-grupy-uhylyantiv/\">\u62a5\u9053\u4e86\u519b\u961f</a>\uff0c\u5728\u8de8\u6258\u5e15\u8482\u4e9a\uff0c\u505c\u6b62\u4e86\u4e24\u7ec4\u8bc1\u636e\u3002</p></div>", "source": "https://armyinform.com.ua/2024/03/26/uhylyanta-z-odesy-vylovyly-v-richczi-z-obmorozhennyamy/", "title": "\u6556\u5fb7\u8428\u4e0e\u51bb\u4f24\u5728\u6cb3\u91cc\u7684\u6556\u5fb7\u8428\u54fc\u4e86\u4e00\u58f0", "description": "\u4e4c\u514b\u5170\u56fd\u5bb6\u8fb9\u5883\u90e8\u95e8\u57283\u670826\u65e5\u62a5\u9053\u4e86\u8fd9\u4e00\u70b9\u3002 \u6839\u636e...", "author": ["Army Inform"], "categories": ["\u041d\u043e\u0432\u0438\u043d\u0438"], "tags": ["\u0414\u041f\u0421\u0423", "\u041e\u0434\u0435\u0449\u0438\u043d\u0430", "\u0443\u0445\u0438\u043b\u044f\u043d\u0442\u0438"], "source_name": "ArmyInform"}