{"published time": "2024-03-26T18:12:00+08:00", "images": ["https://armyinform.com.ua/wp-content/uploads/2024/03/dpsu_udar.png"], "content": "<div class=\"single-content\"><figure class=\"post-thumbnail\"><img alt=\"\" class=\"attachment-post-thumbnail size-post-thumbnail wp-post-image\" height=\"1014\" sizes=\"(max-width: 1920px) 100vw, 1920px\" src=\"../Images/2024-03-26T18-12-00-08-00/000000.png\" srcset=\"../Images/2024-03-26T18-12-00-08-00/000000.png\" width=\"1920\"/></figure><!-- .post-thumbnail --><p><strong>\u5728Bakhmut\u7684\u65b9\u5411\u4e0a\uff0c\u654c\u4eba\u7684BTR-82A\u548c\u4e09\u4e2a\u5165\u4fb5\u8005\u7684\u907f\u96be\u6240\u5728\u51b2\u51fb\u65e0\u4eba\u673a\u7684\u5e2e\u52a9\u4e0b\u88ab\u6e05\u7b97\u3002</strong></p><p>\u9002\u5f53\u7684\u89c6\u9891<a href=\"https://t.me/DPSUkr/19103\" rel=\"nofollow\" target=\"_blank\">\u5979\u4e8e3\u670826\u65e5\u53d1\u5e03</a>\u4e4c\u514b\u5170\u56fd\u5bb6\u8fb9\u5883\u670d\u52a1\u3002</p><p><iframe allowfullscreen=\"allowfullscreen\" frameborder=\"0\" height=\"314\" loading=\"lazy\" scrolling=\"no\" src=\"https://www.facebook.com/plugins/video.php?height=314&amp;href=https%3A%2F%2Fwww.facebook.com%2FDPSUkraine%2Fvideos%2F807754328049873%2F&amp;show_text=false&amp;width=560&amp;t=0\" style=\"border: none; overflow: hidden;\" width=\"560\"></iframe></p><p>\u201c\u590d\u4ec7\u201d\u8fdb\u653b\u5b88\u536b\u7684\u8fb9\u9632\u90e8\u961f\u53d7\u5230\u4e86\u88ad\u51fb\u3002</p><p>\u4f5c\u4e3a<a href=\"https://armyinform.com.ua/2024/03/26/u-dnipropetrovskij-oblasti-zbyly-vorozhu-raketu-h-59/\">\u9646\u519b\u65e9\u4e9b\u65f6\u5019\u62a5\u9053</a>\uff0c\u5728Dnipropetrovsk\u5730\u533a\uff0c\u654c\u65b9\u5bfc\u5f39X-59\u88ab\u51fb\u843d\u3002</p></div>", "source": "https://armyinform.com.ua/2024/03/26/syly-oborony-znyshhyly-try-ukryttya-i-bronetehniku-voroga/", "title": "\u56fd\u9632\u519b\u6467\u6bc1\u4e86\u654c\u4eba\u7684\u4e09\u4e2a\u5e87\u62a4\u6240\u548c\u88c5\u7532\u8f66", "description": "\u76f8\u5173\u89c6\u9891\u7531\u4e4c\u514b\u5170\u5dde\u8fb9\u5883\u670d\u52a1\u90e8\u4e8e3\u670826\u65e5\u53d1\u5e03\u3002 \u5439 ...", "author": ["Army Inform"], "categories": ["\u041d\u043e\u0432\u0438\u043d\u0438"], "tags": ["\u0432\u0442\u0440\u0430\u0442\u0438 \u0432\u043e\u0440\u043e\u0433\u0430", "\u0414\u041f\u0421\u0423", "\u041f\u043e\u043c\u0441\u0442\u0430", "\u0425\u0440\u043e\u043d\u0456\u043a\u0430 \u0432\u0456\u0439\u043d\u0438"], "source_name": "ArmyInform"}