{"published time": "2024-03-18T17:17:00+08:00", "news source": "https://x.com/MVS_UA/status/1769654224072409506/photo/1", "lng": "37.11371", "lat": "50.20363", "location": ["Kharkiv"], "id": 22636440, "action": "bomb-1", "title": "1\u6551\u63f4\u4eba\u5458\u56e0\u4fc4\u7f57\u65af\u7a7a\u88ad\u800c\u53d7\u4f24", "images": [], "content": "<h2>1\u6551\u63f4\u4eba\u5458\u56e0\u4fc4\u7f57\u65af\u7a7a\u88ad\u800c\u53d7\u4f24</h2><div class=\"popup_video\"></div><div class=\"popup_imgi\"></div>", "source": "https://liveuamap.com/en/2024/18-march-1-rescuer-wounded-as-result-of-russian-airstrike", "author": ["Live UA Map"], "categories": [], "tags": ["Kharkiv"], "source_name": "LiveUAMap"}